xenon/__init__.py
xenon/attribute_parser.py
xenon/audit.py
xenon/cli.py
xenon/config.py
xenon/encoding.py
xenon/entities.py
xenon/exceptions.py
xenon/formatting.py
xenon/parser.py
xenon/preprocessor.py
xenon/py.typed
xenon/reporting.py
xenon/security.py
xenon/streaming.py
xenon/trust.py
xenon/utils.py
xenon/validation.py
xenon/integrations/__init__.py
xenon/integrations/langchain.py
elemental_xenon-1.1.0.dist-info/METADATA
elemental_xenon-1.1.0.dist-info/WHEEL
elemental_xenon-1.1.0.dist-info/entry_points.txt
elemental_xenon-1.1.0.dist-info/licenses/LICENSE
elemental_xenon-1.1.0.dist-info/RECORD
