Metadata-Version: 2.4
Name: elemental-xenon
Version: 1.1.0
Summary: Secure-by-default XML repair library for LLM-generated XML with trust levels
Project-URL: Homepage, https://github.com/MarsZDF/xenon
Project-URL: Documentation, https://github.com/MarsZDF/xenon
Project-URL: Repository, https://github.com/MarsZDF/xenon
Project-URL: Bug Tracker, https://github.com/MarsZDF/xenon/issues
Author: Marco Zaccaria Di Fraia, Xenon Contributors
License-Expression: MIT
License-File: LICENSE
Keywords: ai,ai-agents,async,audit,generative-ai,hallucination-repair,llm,malformed,nlp,parser,rag,repair,security,streaming,trust-levels,xml
Classifier: Development Status :: 5 - Production/Stable
Classifier: Intended Audience :: Developers
Classifier: Intended Audience :: Science/Research
Classifier: License :: OSI Approved :: MIT License
Classifier: Operating System :: OS Independent
Classifier: Programming Language :: Python :: 3
Classifier: Programming Language :: Python :: 3.8
Classifier: Programming Language :: Python :: 3.9
Classifier: Programming Language :: Python :: 3.10
Classifier: Programming Language :: Python :: 3.11
Classifier: Programming Language :: Python :: 3.12
Classifier: Programming Language :: Python :: 3.13
Classifier: Topic :: Scientific/Engineering :: Artificial Intelligence
Classifier: Topic :: Security
Classifier: Topic :: Software Development :: Libraries :: Python Modules
Classifier: Topic :: Text Processing
Classifier: Topic :: Text Processing :: Markup :: XML
Classifier: Typing :: Typed
Requires-Python: >=3.8
Provides-Extra: dev
Requires-Dist: bandit>=1.7.0; extra == 'dev'
Requires-Dist: commitizen>=3.0; extra == 'dev'
Requires-Dist: hypothesis>=6.0; extra == 'dev'
Requires-Dist: mypy>=1.0; extra == 'dev'
Requires-Dist: pre-commit>=3.0; extra == 'dev'
Requires-Dist: pytest-asyncio>=0.21.0; extra == 'dev'
Requires-Dist: pytest-benchmark>=4.0; extra == 'dev'
Requires-Dist: pytest-cov>=4.0; extra == 'dev'
Requires-Dist: pytest>=7.0; extra == 'dev'
Requires-Dist: python-semantic-release>=8.0; extra == 'dev'
Requires-Dist: ruff>=0.1.0; extra == 'dev'
Requires-Dist: types-lxml>=2024.0.0; extra == 'dev'
Provides-Extra: lxml
Requires-Dist: lxml>=4.9.0; extra == 'lxml'
